{
  "stores": [
    {
      "store": {
        "name": "Selecione"
      },
      "location": {
        "city": "Escolha a Cidade",
        "state": ""
      },
      "whatsapp": ""
    },
    {
      "store": {
        "name": "Mercadão dos Óculos de Tabatinga"
      },
      "location": {
        "city": "Tabatinga - SP",
        "state": "São Paulo"
      },
      "whatsapp": "https://api.whatsapp.com/send?phone=5516996001026"
    },
    {
      "store": {
        "name": "Mercadão dos Óculos de Potirendaba"
      },
      "location": {
        "city": "Potirendaba - SP",
        "state": "São Paulo"
      },
      "whatsapp": "https://api.whatsapp.com/send?phone=5517996509700"
    },
    {
      "store": {
        "name": "Mercadão dos Óculos de Olímpia"
      },
      "location": {
        "city": "Olímpia - SP",
        "state": "São Paulo"
      },
      "whatsapp": "https://api.whatsapp.com/send?phone=5517997014171"
    },
    {
      "store": {
        "name": "Mercadão dos Óculos de Taquaritinga"
      },
      "location": {
        "city": "Taquaritinga - SP",
        "state": "São Paulo"
      },
      "whatsapp": "https://api.whatsapp.com/send?phone=5516996139668"
    },
    {
      "store": {
        "name": "Mercadão dos Óculos Tubarão - SC"
      },
      "location": {
        "city": "Tubarão - SC",
        "state": "Santa Catarina"
      },
      "whatsapp": "https://api.whatsapp.com/send?phone=554899771002"
    },
    {
      "store": {
        "name": "Mercadão dos Óculos Panambi - RS"
      },
      "location": {
        "city": "Panambi - RS",
        "state": "Rio Grande do Sul"
      },
      "whatsapp": "https://api.whatsapp.com/send?phone=5555992301212"
    },
    {
      "store": {
        "name": "Mercadão dos Óculos Tubarão Oficinas - SC"
      },
      "location": {
        "city": "Tubarão Oficinas - SC",
        "state": "Santa Catarina"
      },
      "whatsapp": "https://api.whatsapp.com/send?phone=554892088787"
    },
    {
      "store": {
        "name": "Mercadão dos Óculos Canoas - RS"
      },
      "location": {
        "city": "Canoas - RS",
        "state": "Rio Grande do Sul"
      },
      "whatsapp": "https://api.whatsapp.com/send?phone=555191489295"
    },
    {
      "store": {
        "name": "Mercadão dos Óculos Porto Alegre - RS"
      },
      "location": {
        "city": "Porto Alegre - RS",
        "state": "Rio Grande do Sul"
      },
      "whatsapp": "https://api.whatsapp.com/send?phone=555180648629"
    },
    {
      "store": {
        "name": "Mercadão dos Óculos São Carlos - SP"
      },
      "location": {
        "city": "São Carlos - SP",
        "state": "São Paulo"
      },
      "whatsapp": "https://api.whatsapp.com/send?phone=5516993240269"
    },
    {
      "store": {
        "name": "Mercadão dos Óculos Lins - SP"
      },
      "location": {
        "city": "Lins - SP",
        "state": "São Paulo"
      },
      "whatsapp": "https://api.whatsapp.com/send?phone=5514991716850"
    },
    {
      "store": {
        "name": "Mercadão dos Óculos Birigui - SP"
      },
      "location": {
        "city": "Birigui - SP",
        "state": "São Paulo"
      },
      "whatsapp": "https://api.whatsapp.com/send?phone=5518996966850"
    },
    {
      "store": {
        "name": "Mercadão dos Óculos Araçatuba - SP"
      },
      "location": {
        "city": "Araçatuba - SP",
        "state": "São Paulo"
      },
      "whatsapp": "https://api.whatsapp.com/send?phone=5518997006850"
    },
    {
      "store": {
        "name": "Mercadão dos Óculos Mangabeira - PB"
      },
      "location": {
        "city": "Mangabeira - PB",
        "state": "Paraíba"
      },
      "whatsapp": "https://api.whatsapp.com/send?phone=5583991109090"
    },
    {
      "store": {
        "name": "Mercadão dos Óculos Mogi Guaçu - SP"
      },
      "location": {
        "city": "Mogi Guaçu - SP",
        "state": "São Paulo"
      },
      "whatsapp": "https://api.whatsapp.com/send?phone=5519971111444"
    }
  ]
}
